file_2.v
module memory #(
    parameter MEM_SIZE = 6,
    parameter DATA_W = 10,
    parameter ADDR_SIZE = $clog2(MEM_SIZE)
)(
    input wire clk,
    input wire write_flag,
    input wire [DATA_W-1:0] data_in,
    input wire [ADDR_SIZE-1:0] addr_w,
    input wire read_flag,
    input wire [ADDR_SIZE-1:0] addr_r,
    output reg [DATA_W-1:0] data_out
);

reg [DATA_W-1:0] memory [MEM_SIZE-1:0];

always @(posedge clk) begin
    if (write_flag) memory[addr_w] <= data_in;
end

always @(posedge clk) begin
    if (read_flag) data_out <= memory[addr_r];
end

endmodule

file_2_tb.v
`timescale 1ns/1ns

module memory_tb();

parameter MEM_SIZE = 6;
parameter DATA_W = 10;
localparam ADDR_SIZE = $clog2(MEM_SIZE);

reg clk;
reg write_flag;
reg [DATA_W-1:0] data_in;
reg [ADDR_SIZE-1:0] addr_w;
reg read_flag;
reg [ADDR_SIZE-1:0] addr_r;
wire [DATA_W-1:0] data_out;

memory #(.MEM_SIZE(MEM_SIZE), .DATA_W(DATA_W)) test_module (.clk(clk), .write_flag(write_flag), .data_in(data_in), .addr_w(addr_w), .read_flag(read_flag), .addr_r(addr_r), .data_out(data_out));

initial begin
    clk = 0;
    forever #5 clk = ~clk;
end

initial begin
    $dumpvars;
end

initial begin
    write_flag = 0;
    read_flag = 0;
    data_in = 0;
    addr_w = 0;
    addr_r = 0;
    #10;
    
    write_flag = 1;
    data_in = 10'h123;
    addr_w = 3'b000;
    #10;

    write_flag = 0;
    read_flag = 1;
    addr_r = 3'b000;
    #10;
    
    write_flag = 1;
    read_flag = 1;
    data_in = 10'hBC;
    addr_w = 3'b001;
    addr_r = 3'b001;
    #10;
    
    write_flag = 0;    
    read_flag = 1;
    #10;
    
    read_flag = 0;
    #10;

    write_flag = 1;
    read_flag = 1;
    data_in = 10'hDF;
    addr_w = 3'b010;
    addr_r = 3'b011;
    #20;
    
    $finish;
end

endmodule

file_1.v
module check_divisibility #(
    parameter DATA_W = 8
)(
    input wire [DATA_W-1:0] data, 
    output reg divisibility
    // output reg sum_even_reg,
    // output reg sum_odd_reg
);

integer i;
integer sum_even, sum_odd;
integer even_count, odd_count;
integer inverted_sum;


always @(*) 
begin
    sum_even = 0; //Сумма битов на четных позициях
    sum_odd = 0;  //Сумма битов на нечетных позициях

    even_count = 0;
    odd_count = 0;
    
    for (i = 0; i < DATA_W; i = i + 1) 
    begin
        if (i % 2 == 0) 
        begin
            sum_even = sum_even + data[i]; //Здесь вычисляем соответственно сумму на четных
            even_count = even_count + 1;
        end 
        else 
        begin
            sum_odd = sum_odd + data[i];   //А здесь на нечетных
            odd_count = odd_count + 1;
        end
    end
    inverted_sum = ((even_count - sum_even) - (odd_count - sum_odd))%3;
    if (data[DATA_W-1] == 0 && (sum_even - sum_odd)%3==0 || data[DATA_W-1] == 1 && (inverted_sum == -1 || inverted_sum == 2))
    begin
        divisibility <= 1'b1; 
    end
    else
    begin
        divisibility <= 1'b0; 
    end

    // sum_even_reg <= sum_even;
    // sum_odd_reg <= sum_odd;
    /*Признак делимости на 3 в двоичной системе счисления звучит следующим образом: 
    «Число делится на 3 тогда и только тогда, когда сумма его цифр стоящих на четных местах отличается от суммы цифр, 
    стоящих на нечетных местах, на число, делящееся на 3». Например, 21 = 10101. Для него сумма цифр на 
    нечетных местах равна 1 + 1 + 1 = 3, а на четных — 0 + 0 = 0. Признак выполняется, и число делится на 3.
    */
end

endmodule

file_1_tb.v
`timescale 1ns/1ns

module check_divisibility_tb();

parameter DATA_W = 8;
reg [DATA_W-1:0] data;
wire divisibility;

check_divisibility #(.DATA_W(DATA_W)) test_module (.data(data), .divisibility(divisibility));

//Таймер по ТЗ не предусмотрен

initial begin
    $dumpvars;
end

initial begin
    data = 8'b00000011;  // 3
    #10;
    
    data = 8'b00000110;  // 6
    #10;
    
    data = 8'b11111101;  // -3
    #10;
    
    data = 8'b11111010;  // -6 
    #10;
    
    data = 8'b00000001;  // 1
    #10;
    
    data = 8'b11111111;  // -1
    #10;
    
    data = 8'b00000100;  // 4
    #10;
    
    data = 8'b11111100;  // -4
    #10;
    
    $finish;
end

endmodule

dump.vcd
$date
	Tue Apr 22 17:09:35 2025
$end
$version
	Icarus Verilog
$end
$timescale
	1ns
$end
$scope module check_divisibility_tb $end
$var wire 1 ! divisibility $end
$var reg 8 " data [7:0] $end
$scope module test_module $end
$var wire 8 # data [7:0] $end
$var reg 1 ! divisibility $end
$var integer 32 $ even_count [31:0] $end
$var integer 32 % i [31:0] $end
$var integer 32 & inverted_sum [31:0] $end
$var integer 32 ' odd_count [31:0] $end
$var integer 32 ( sum_even [31:0] $end
$var integer 32 ) sum_odd [31:0] $end
$upscope $end
$upscope $end
$scope module memory_tb $end
$var wire 10 * data_out [9:0] $end
$var reg 3 + addr_r [2:0] $end
$var reg 3 , addr_w [2:0] $end
$var reg 1 - clk $end
$var reg 10 . data_in [9:0] $end
$var reg 1 / read_flag $end
$var reg 1 0 write_flag $end
$scope module test_module $end
$var wire 3 1 addr_r [2:0] $end
$var wire 3 2 addr_w [2:0] $end
$var wire 1 - clk $end
$var wire 10 3 data_in [9:0] $end
$var wire 1 / read_flag $end
$var wire 1 0 write_flag $end
$var reg 10 4 data_out [9:0] $end
$upscope $end
$upscope $end
$scope module check_divisibility_tb $end
$scope module test_module $end
$upscope $end
$upscope $end
$scope module memory_tb $end
$scope module test_module $end
$upscope $end
$upscope $end
$enddefinitions $end
#0
$dumpvars
bx 4
b0 3
b0 2
b0 1
00
0/
b0 .
0-
b0 ,
b0 +
bx *
b1 )
b1 (
b100 '
b0 &
b1000 %
b100 $
b11 #
b11 "
1!
$end
#5
1-
#10
b1000 %
b100 '
b100 $
b1 )
b1 (
0-
b100100011 .
b100100011 3
10
b110 "
b110 #
#15
1-
#20
b11111111111111111111111111111111 &
b1000 %
b100 '
b100 $
b11 )
b100 (
0-
1/
00
b11111101 "
b11111101 #
#25
b100100011 *
b100100011 4
1-
#30
b10 &
b1000 %
b100 '
b100 $
b100 )
b10 (
0-
b1 +
b1 1
b1 ,
b1 2
b10111100 .
b10111100 3
10
b11111010 "
b11111010 #
#35
bx *
bx 4
1-
#40
0!
b11111111111111111111111111111111 &
b1000 %
b100 '
b100 $
b0 )
b1 (
0-
00
b1 "
b1 #
#45
b10111100 *
b10111100 4
1-
#50
b0 &
b100 )
b1000 %
b100 '
b100 $
b100 (
0-
0/
b11111111 "
b11111111 #
#55
1-
#60
b11111111111111111111111111111111 &
b1000 %
b100 '
b100 $
b0 )
b1 (
0-
b11 +
b11 1
b10 ,
b10 2
b11011111 .
b11011111 3
1/
10
b100 "
b100 #
#65
bx *
bx 4
1-
#70
b0 &
b11 )
b1000 %
b100 '
b100 $
b11 (
0-
b11111100 "
b11111100 #
